[
  {
    "id": 1,
    "type": "fedearal",
    "name": "number1"
  },
  {
    "id": 2,
    "type": "fedearal",
    "name": "number2"
  },
  {
    "id": 3,
    "type": "fedearal",
    "name": "numbejGG2196"
  },
  {
    "id": 4,
    "type": "fedearal",
    "name": "numbejGG2403"
  },
  {
    "id": 5,
    "type": "fedearal",
    "name": "numbejGG2367"
  },
  {
    "id": 6,
    "type": "fedearal",
    "name": "numbejGG2146"
  },
  {
    "id": 7,
    "type": "fedearal",
    "name": "numbejGG2876"
  },
  {
    "id": 8,
    "type": "fedearal",
    "name": "numbejGG2951"
  },
  {
    "id": 9,
    "type": "fedearal",
    "name": "numbejGG2398"
  }
]